MANIFEST.in
pyproject.toml
setup.py
ceto/__init__.py
ceto/__main__.py
ceto/abstractsyntaxtree.py
ceto/codegen.py
ceto/compiler.py
ceto/indentchecker.py
ceto/parser.py
ceto/preprocessor.py
ceto/pythonfrontend.py
ceto/semanticanalysis.py
ceto.egg-info/PKG-INFO
ceto.egg-info/SOURCES.txt
ceto.egg-info/dependency_links.txt
ceto.egg-info/entry_points.txt
ceto.egg-info/not-zip-safe
ceto.egg-info/requires.txt
ceto.egg-info/top_level.txt
include/ceto.h
selfhost/ast.cpp
selfhost/ast.ctp