Metadata-Version: 2.1
Name: ceto
Version: 0.1.1
Summary: General purpose programming language transpiled to C++
Home-page: https://github.com/ehren/ceto
Author: Ehren Metcalfe
Author-email: ehren.m@gmail.com
Requires-Python: >=3.8
Provides-Extra: test
